asrpy/__init__.py
asrpy/asr.py
asrpy/asr_utils.py
asrpy_eh-0.0.5.dist-info/LICENSE
asrpy_eh-0.0.5.dist-info/METADATA
asrpy_eh-0.0.5.dist-info/WHEEL
asrpy_eh-0.0.5.dist-info/top_level.txt
asrpy_eh-0.0.5.dist-info/RECORD
